pilottai/__init__.py
pilottai/agent/__init__.py
pilottai/agent/action_agent.py
pilottai/agent/agent.py
pilottai/agent/master_agent.py
pilottai/agent/super_agent.py
pilottai/config/config.py
pilottai/config/model.py
pilottai/core/__init__.py
pilottai/core/base_agent.py
pilottai/core/base_config.py
pilottai/core/base_job.py
pilottai/delegation/task_delegator.py
pilottai/engine/llm.py
pilottai/enums/__init__.py
pilottai/enums/agent_e.py
pilottai/enums/health_e.py
pilottai/enums/job_e.py
pilottai/enums/process_e.py
pilottai/enums/tool_e.py
pilottai/enums/type_e.py
pilottai/examples/__init__.py
pilottai/examples/customer_service.py
pilottai/examples/document_processing.py
pilottai/examples/email_service.py
pilottai/examples/marketing_expert.py
pilottai/examples/research_analyst.py
pilottai/examples/sales_rep.py
pilottai/examples/social_media_manager.py
pilottai/examples/teacher.py
pilottai/examples/web_search.py
pilottai/job/__init__.py
pilottai/job/delegator.py
pilottai/job/job.py
pilottai/job/router.py
pilottai/memory/controller.py
pilottai/memory/memory.py
pilottai/orchestration/__init__.py
pilottai/orchestration/load_balancer.py
pilottai/orchestration/orchestration.py
pilottai/orchestration/scaling.py
pilottai/pilott.py
pilottai/rules/rules.yaml
pilottai/tools/__init__.py
pilottai/tools/tool.py
pilottai/utils/__init__.py
pilottai/utils/agent_utils.py
pilottai/utils/common_utils.py
pilottai/utils/excpetions/agent.py
pilottai/utils/excpetions/base.py
pilottai/utils/excpetions/config.py
pilottai/utils/excpetions/llm.py
pilottai/utils/excpetions/memory.py
pilottai/utils/excpetions/task.py
pilottai/utils/excpetions/tools.py
pilottai/utils/formatter.py
pilottai/utils/job_utils.py
pilottai/utils/logger.py
pilottai-0.2.7.37.dist-info/LICENSE
pilottai-0.2.7.37.dist-info/METADATA
pilottai-0.2.7.37.dist-info/WHEEL
pilottai-0.2.7.37.dist-info/RECORD
