Metadata-Version: 2.3
Name: pilottai
Version: 0.2.7.37
Summary: A for building scalable multi-agent systems with built-in orchestration,LLM integration, and intelligent job processing.
Author: Anuj Gupta
Author-email: anuj@pilottai.com
Requires-Python: >=3.10,<4.0
Classifier: Programming Language :: Python :: 3
Classifier: Programming Language :: Python :: 3.10
Classifier: Programming Language :: Python :: 3.11
Classifier: Programming Language :: Python :: 3.12
Classifier: Programming Language :: Python :: 3.13
Requires-Dist: cryptography (>=45.0.5,<46.0.0)
Requires-Dist: litellm (>=1.74.6,<2.0.0)
Requires-Dist: markdown (>=3.7,<4.0)
Requires-Dist: numpy (>=2.2.6,<3.0.0)
Requires-Dist: pandas (>=2.2.3,<3.0.0)
Requires-Dist: psutil (>=7.0.0,<8.0.0)
Requires-Dist: pydantic (>=2.7.1,<3.0.0)
Requires-Dist: pydantic-settings (>=2.2.1,<3.0.0)
Project-URL: Docs, https://docs.pilottai.com
Project-URL: Homepage, https://pilottai.com
